spaceTree/__init__.py
spaceTree/dataset.py
spaceTree/main.py
spaceTree/models.py
spaceTree/plot_spatial.py
spaceTree/plotting.py
spaceTree/preprocessing.py
spaceTree/utils.py
spaceTree-0.1.8.dist-info/LICENSE
spaceTree-0.1.8.dist-info/METADATA
spaceTree-0.1.8.dist-info/WHEEL
spaceTree-0.1.8.dist-info/top_level.txt
spaceTree-0.1.8.dist-info/RECORD
