Metadata-Version: 2.1
Name: spaceTree
Version: 0.1.8
Summary: PyPI package for multi-task label transfer from single-cell refrence data to spatial data
Home-page: https://github.com/PMBio/spaceTree
Author: Olga Lazareva et al.
Author-email: olazareva1993@gmail.com
Classifier: Programming Language :: Python :: 3.10
Classifier: License :: OSI Approved :: MIT License
Classifier: Operating System :: OS Independent
Requires-Python: >=3.10
License-File: LICENSE
Requires-Dist: numpy
Requires-Dist: pandas
Requires-Dist: scikit-learn
Requires-Dist: scipy
Requires-Dist: matplotlib
Requires-Dist: seaborn
Requires-Dist: h5py
Requires-Dist: torch>=2.0.1
Requires-Dist: torchvision
Requires-Dist: torchaudio
Requires-Dist: requests
Requires-Dist: openpyxl
Requires-Dist: absl-py
Requires-Dist: aiobotocore
Requires-Dist: aiohttp
Requires-Dist: aiosignal
Requires-Dist: anndata
Requires-Dist: async-timeout
Requires-Dist: attrs
Requires-Dist: botocore
Requires-Dist: chex
Requires-Dist: cloudpickle
Requires-Dist: dask
Requires-Dist: dask-image
Requires-Dist: datashader
Requires-Dist: distributed
Requires-Dist: flax
Requires-Dist: geopandas
Requires-Dist: infercnvpy
Requires-Dist: jax
Requires-Dist: jaxlib
Requires-Dist: joblib
Requires-Dist: pytorch-lightning
Requires-Dist: scanpy
Requires-Dist: scvi-tools
Requires-Dist: tqdm
Requires-Dist: umap-learn
